customtkinter/__init__.py
customtkinter/windows/__init__.py
customtkinter/windows/ctk_input_dialog.py
customtkinter/windows/ctk_tk.py
customtkinter/windows/ctk_toplevel.py
customtkinter/windows/icon.py
customtkinter/windows/widgets/__init__.py
customtkinter/windows/widgets/ctk_button.py
customtkinter/windows/widgets/ctk_checkbox.py
customtkinter/windows/widgets/ctk_combobox.py
customtkinter/windows/widgets/ctk_entry.py
customtkinter/windows/widgets/ctk_frame.py
customtkinter/windows/widgets/ctk_label.py
customtkinter/windows/widgets/ctk_optionmenu.py
customtkinter/windows/widgets/ctk_progressbar.py
customtkinter/windows/widgets/ctk_radiobutton.py
customtkinter/windows/widgets/ctk_scrollable_frame.py
customtkinter/windows/widgets/ctk_scrollbar.py
customtkinter/windows/widgets/ctk_segmented_button.py
customtkinter/windows/widgets/ctk_slider.py
customtkinter/windows/widgets/ctk_switch.py
customtkinter/windows/widgets/ctk_tabview.py
customtkinter/windows/widgets/ctk_textbox.py
customtkinter/windows/widgets/appearance_mode/__init__.py
customtkinter/windows/widgets/appearance_mode/appearance_mode_base_class.py
customtkinter/windows/widgets/appearance_mode/appearance_mode_tracker.py
customtkinter/windows/widgets/core_rendering/__init__.py
customtkinter/windows/widgets/core_rendering/ctk_canvas.py
customtkinter/windows/widgets/core_rendering/draw_engine.py
customtkinter/windows/widgets/core_widget_classes/__init__.py
customtkinter/windows/widgets/core_widget_classes/ctk_base_class.py
customtkinter/windows/widgets/core_widget_classes/dropdown_menu.py
customtkinter/windows/widgets/font/__init__.py
customtkinter/windows/widgets/font/ctk_font.py
customtkinter/windows/widgets/font/font_manager.py
customtkinter/windows/widgets/font/fonts.py
customtkinter/windows/widgets/image/__init__.py
customtkinter/windows/widgets/image/ctk_image.py
customtkinter/windows/widgets/scaling/__init__.py
customtkinter/windows/widgets/scaling/scaling_base_class.py
customtkinter_pyinstaller-5.1.2.dist-info/LICENSE
customtkinter_pyinstaller-5.1.2.dist-info/METADATA
customtkinter_pyinstaller-5.1.2.dist-info/WHEEL
customtkinter_pyinstaller-5.1.2.dist-info/top_level.txt
customtkinter_pyinstaller-5.1.2.dist-info/RECORD
