Metadata-Version: 2.1
Name: customtkinter-pyinstaller
Version: 5.1.2
Summary: A modern and customizable python UI-library based on Tkinter modified to work with pyinstaller onefile
Home-page: https://github.com/westhecool/CustomTkinter-for-pyinstaller
Author: westhecool
Author-email: 
License: Creative Commons Zero v1.0 Universal
Classifier: License :: CC0 1.0 Universal (CC0 1.0) Public Domain Dedication
Classifier: Operating System :: OS Independent
Classifier: Programming Language :: Python :: 3 :: Only
Requires-Python: >=3.7
License-File: LICENSE
Requires-Dist: darkdetect
Requires-Dist: typing-extensions ; python_version <= "3.7"
